[
  {
    "Type": "Incus",
    "Os": "Almalinux",
    "Distribution": "Almalinux",
    "Name": "almalinux",
    "Username": "root",
    "Uid": 0,
    "Release": "10",
    "Url": "https://images.linuxcontainers.org/images/almalinux/10/amd64/default/20260125_23%3A08/rootfs.tar.xz",
    "Configured": false,
    "LocalFileName": "D86D17E596520F87F00D8911AD46187A6720AB0638ADB3ED9EB5243F8202982C.rootfs.tar.gz",
    "Hash": {
      "Url": "https://images.linuxcontainers.org/images/almalinux/10/amd64/default/20260125_23%3A08/SHA256SUMS",
      "Type": "sums",
      "Algorithm": "SHA256"
    },
    "Digest": "D86D17E596520F87F00D8911AD46187A6720AB0638ADB3ED9EB5243F8202982C",
    "Size": 83872580,
    "Tags": [
      "10"
    ]
  },
  {
    "Type": "Incus",
    "Os": "Almalinux",
    "Distribution": "Almalinux",
    "Name": "almalinux",
    "Username": "root",
    "Uid": 0,
    "Release": "8",
    "Url": "https://images.linuxcontainers.org/images/almalinux/8/amd64/default/20260125_23%3A08/rootfs.tar.xz",
    "Configured": false,
    "LocalFileName": "436DC8CB1486EF9F910C30AE526836CE30F6169E930935F6C565567F5D815F9B.rootfs.tar.gz",
    "Hash": {
      "Url": "https://images.linuxcontainers.org/images/almalinux/8/amd64/default/20260125_23%3A08/SHA256SUMS",
      "Type": "sums",
      "Algorithm": "SHA256"
    },
    "Digest": "436DC8CB1486EF9F910C30AE526836CE30F6169E930935F6C565567F5D815F9B",
    "Size": 115490932,
    "Tags": [
      "8"
    ]
  },
  {
    "Type": "Incus",
    "Os": "Almalinux",
    "Distribution": "Almalinux",
    "Name": "almalinux",
    "Username": "root",
    "Uid": 0,
    "Release": "9",
    "Url": "https://images.linuxcontainers.org/images/almalinux/9/amd64/default/20260125_23%3A08/rootfs.tar.xz",
    "Configured": false,
    "LocalFileName": "77DBF5F04C5C2637F6C43E94530E5027D844CA9C4085E72BC7A78100B460E7E6.rootfs.tar.gz",
    "Hash": {
      "Url": "https://images.linuxcontainers.org/images/almalinux/9/amd64/default/20260125_23%3A08/SHA256SUMS",
      "Type": "sums",
      "Algorithm": "SHA256"
    },
    "Digest": "77DBF5F04C5C2637F6C43E94530E5027D844CA9C4085E72BC7A78100B460E7E6",
    "Size": 106726468,
    "Tags": [
      "9"
    ]
  },
  {
    "Type": "Incus",
    "Os": "Alpine",
    "Distribution": "Alpine",
    "Name": "alpine",
    "Username": "root",
    "Uid": 0,
    "Release": "3.20",
    "Url": "https://images.linuxcontainers.org/images/alpine/3.20/amd64/default/20260125_13%3A00/rootfs.tar.xz",
    "Configured": false,
    "LocalFileName": "FF29BF4491DA7E6E9A2B325B6F81CE265F7DBBC401DBE1D7668711C5EBB1B058.rootfs.tar.gz",
    "Hash": {
      "Url": "https://images.linuxcontainers.org/images/alpine/3.20/amd64/default/20260125_13%3A00/SHA256SUMS",
      "Type": "sums",
      "Algorithm": "SHA256"
    },
    "Digest": "FF29BF4491DA7E6E9A2B325B6F81CE265F7DBBC401DBE1D7668711C5EBB1B058",
    "Size": 3138912,
    "Tags": [
      "3.20"
    ]
  },
  {
    "Type": "Incus",
    "Os": "Alpine",
    "Distribution": "Alpine",
    "Name": "alpine",
    "Username": "root",
    "Uid": 0,
    "Release": "3.21",
    "Url": "https://images.linuxcontainers.org/images/alpine/3.21/amd64/default/20260125_13%3A00/rootfs.tar.xz",
    "Configured": false,
    "LocalFileName": "2B1110494395193997D381BF54E4853E85D91F6EF623F4BA035F0A554F488E7E.rootfs.tar.gz",
    "Hash": {
      "Url": "https://images.linuxcontainers.org/images/alpine/3.21/amd64/default/20260125_13%3A00/SHA256SUMS",
      "Type": "sums",
      "Algorithm": "SHA256"
    },
    "Digest": "2B1110494395193997D381BF54E4853E85D91F6EF623F4BA035F0A554F488E7E",
    "Size": 3154788,
    "Tags": [
      "3.21"
    ]
  },
  {
    "Type": "Incus",
    "Os": "Alpine",
    "Distribution": "Alpine",
    "Name": "alpine",
    "Username": "root",
    "Uid": 0,
    "Release": "3.22",
    "Url": "https://images.linuxcontainers.org/images/alpine/3.22/amd64/default/20260125_13%3A00/rootfs.tar.xz",
    "Configured": false,
    "LocalFileName": "43CDFCEB68AC9B366ED109D0553A6A80A25CCFE05DD282B13AB730E7663921FF.rootfs.tar.gz",
    "Hash": {
      "Url": "https://images.linuxcontainers.org/images/alpine/3.22/amd64/default/20260125_13%3A00/SHA256SUMS",
      "Type": "sums",
      "Algorithm": "SHA256"
    },
    "Digest": "43CDFCEB68AC9B366ED109D0553A6A80A25CCFE05DD282B13AB730E7663921FF",
    "Size": 3275356,
    "Tags": [
      "3.22"
    ]
  },
  {
    "Type": "Incus",
    "Os": "Alpine",
    "Distribution": "Alpine",
    "Name": "alpine",
    "Username": "root",
    "Uid": 0,
    "Release": "3.23",
    "Url": "https://images.linuxcontainers.org/images/alpine/3.23/amd64/default/20260125_13%3A00/rootfs.tar.xz",
    "Configured": false,
    "LocalFileName": "2615D73CAB6DFF5DA5C82A9ABB83E082D3D4A69148D4DA6263D16E208C6C5D97.rootfs.tar.gz",
    "Hash": {
      "Url": "https://images.linuxcontainers.org/images/alpine/3.23/amd64/default/20260125_13%3A00/SHA256SUMS",
      "Type": "sums",
      "Algorithm": "SHA256"
    },
    "Digest": "2615D73CAB6DFF5DA5C82A9ABB83E082D3D4A69148D4DA6263D16E208C6C5D97",
    "Size": 3321864,
    "Tags": [
      "3.23"
    ]
  },
  {
    "Type": "Incus",
    "Os": "Alpine",
    "Distribution": "Alpine",
    "Name": "alpine",
    "Username": "root",
    "Uid": 0,
    "Release": "edge",
    "Url": "https://images.linuxcontainers.org/images/alpine/edge/amd64/default/20260125_13%3A00/rootfs.tar.xz",
    "Configured": false,
    "LocalFileName": "C0CB273A39F09012D4BE2C8B6A4FB11C8DE0D7C5BD14359E40F2DE99E9BFC2F4.rootfs.tar.gz",
    "Hash": {
      "Url": "https://images.linuxcontainers.org/images/alpine/edge/amd64/default/20260125_13%3A00/SHA256SUMS",
      "Type": "sums",
      "Algorithm": "SHA256"
    },
    "Digest": "C0CB273A39F09012D4BE2C8B6A4FB11C8DE0D7C5BD14359E40F2DE99E9BFC2F4",
    "Size": 3322348,
    "Tags": [
      "edge"
    ]
  },
  {
    "Type": "Incus",
    "Os": "Alt",
    "Distribution": "Alt",
    "Name": "alt",
    "Username": "root",
    "Uid": 0,
    "Release": "Sisyphus",
    "Url": "https://images.linuxcontainers.org/images/alt/Sisyphus/amd64/default/20260125_01%3A17/rootfs.tar.xz",
    "Configured": false,
    "LocalFileName": "7629DF465036A5FC4FD6266584D697336ACB70960DD03EC94468C7E5296B3E50.rootfs.tar.gz",
    "Hash": {
      "Url": "https://images.linuxcontainers.org/images/alt/Sisyphus/amd64/default/20260125_01%3A17/SHA256SUMS",
      "Type": "sums",
      "Algorithm": "SHA256"
    },
    "Digest": "7629DF465036A5FC4FD6266584D697336ACB70960DD03EC94468C7E5296B3E50",
    "Size": 217166048,
    "Tags": [
      "Sisyphus"
    ]
  },
  {
    "Type": "Incus",
    "Os": "Alt",
    "Distribution": "Alt",
    "Name": "alt",
    "Username": "root",
    "Uid": 0,
    "Release": "p11",
    "Url": "https://images.linuxcontainers.org/images/alt/p11/amd64/default/20260125_01%3A17/rootfs.tar.xz",
    "Configured": false,
    "LocalFileName": "BCA5FBBF1DBBE9017816853583E842ACEA193331EC572A2D63ADE413A28E53CB.rootfs.tar.gz",
    "Hash": {
      "Url": "https://images.linuxcontainers.org/images/alt/p11/amd64/default/20260125_01%3A17/SHA256SUMS",
      "Type": "sums",
      "Algorithm": "SHA256"
    },
    "Digest": "BCA5FBBF1DBBE9017816853583E842ACEA193331EC572A2D63ADE413A28E53CB",
    "Size": 221180400,
    "Tags": [
      "p11"
    ]
  },
  {
    "Type": "Incus",
    "Os": "Amazonlinux",
    "Distribution": "Amazonlinux",
    "Name": "amazonlinux",
    "Username": "root",
    "Uid": 0,
    "Release": "2023",
    "Url": "https://images.linuxcontainers.org/images/amazonlinux/2023/amd64/default/20260125_05%3A09/rootfs.tar.xz",
    "Configured": false,
    "LocalFileName": "1E716AF0E57538E18F7855AC9B5900C2304A21DA0E1432F2D6A50517B7FAF3B9.rootfs.tar.gz",
    "Hash": {
      "Url": "https://images.linuxcontainers.org/images/amazonlinux/2023/amd64/default/20260125_05%3A09/SHA256SUMS",
      "Type": "sums",
      "Algorithm": "SHA256"
    },
    "Digest": "1E716AF0E57538E18F7855AC9B5900C2304A21DA0E1432F2D6A50517B7FAF3B9",
    "Size": 59830596,
    "Tags": [
      "2023"
    ]
  },
  {
    "Type": "Incus",
    "Os": "Amazonlinux",
    "Distribution": "Amazonlinux",
    "Name": "amazonlinux",
    "Username": "root",
    "Uid": 0,
    "Release": "2",
    "Url": "https://images.linuxcontainers.org/images/amazonlinux/2/amd64/default/20260125_05%3A09/rootfs.tar.xz",
    "Configured": false,
    "LocalFileName": "5910AED041522FBA0FD4199AA62C64B0B7C09D02C4346DDFEB2D2F5B5A6415AD.rootfs.tar.gz",
    "Hash": {
      "Url": "https://images.linuxcontainers.org/images/amazonlinux/2/amd64/default/20260125_05%3A09/SHA256SUMS",
      "Type": "sums",
      "Algorithm": "SHA256"
    },
    "Digest": "5910AED041522FBA0FD4199AA62C64B0B7C09D02C4346DDFEB2D2F5B5A6415AD",
    "Size": 56763100,
    "Tags": [
      "2"
    ]
  },
  {
    "Type": "Incus",
    "Os": "Archlinux",
    "Distribution": "Archlinux",
    "Name": "archlinux",
    "Username": "root",
    "Uid": 0,
    "Release": "current",
    "Url": "https://images.linuxcontainers.org/images/archlinux/current/amd64/default/20260125_04%3A18/rootfs.tar.xz",
    "Configured": false,
    "LocalFileName": "F3A69BBAE00E31E718F87CF59883AFEE03F60ADF3737C13D343BF2A6630CAA91.rootfs.tar.gz",
    "Hash": {
      "Url": "https://images.linuxcontainers.org/images/archlinux/current/amd64/default/20260125_04%3A18/SHA256SUMS",
      "Type": "sums",
      "Algorithm": "SHA256"
    },
    "Digest": "F3A69BBAE00E31E718F87CF59883AFEE03F60ADF3737C13D343BF2A6630CAA91",
    "Size": 204093560,
    "Tags": [
      "current"
    ]
  },
  {
    "Type": "Incus",
    "Os": "Busybox",
    "Distribution": "Busybox",
    "Name": "busybox",
    "Username": "root",
    "Uid": 0,
    "Release": "1.36.1",
    "Url": "https://images.linuxcontainers.org/images/busybox/1.36.1/amd64/default/20260125_06%3A00/rootfs.tar.xz",
    "Configured": false,
    "LocalFileName": "BEB19688CDAE7C8358109D41DD0D8B102AB386F3C58D919C4E594BC6E75CF21D.rootfs.tar.gz",
    "Hash": {
      "Url": "https://images.linuxcontainers.org/images/busybox/1.36.1/amd64/default/20260125_06%3A00/SHA256SUMS",
      "Type": "sums",
      "Algorithm": "SHA256"
    },
    "Digest": "BEB19688CDAE7C8358109D41DD0D8B102AB386F3C58D919C4E594BC6E75CF21D",
    "Size": 1056216,
    "Tags": [
      "1.36.1"
    ]
  },
  {
    "Type": "Incus",
    "Os": "Centos",
    "Distribution": "Centos",
    "Name": "centos",
    "Username": "root",
    "Uid": 0,
    "Release": "10-Stream",
    "Url": "https://images.linuxcontainers.org/images/centos/10-Stream/amd64/default/20260125_07%3A08/rootfs.tar.xz",
    "Configured": false,
    "LocalFileName": "C05D53EAAB6A866722D5F7ED5DA9F9F88F90C0C45B98849BB65AA2BE8DC081B5.rootfs.tar.gz",
    "Hash": {
      "Url": "https://images.linuxcontainers.org/images/centos/10-Stream/amd64/default/20260125_07%3A08/SHA256SUMS",
      "Type": "sums",
      "Algorithm": "SHA256"
    },
    "Digest": "C05D53EAAB6A866722D5F7ED5DA9F9F88F90C0C45B98849BB65AA2BE8DC081B5",
    "Size": 86361784,
    "Tags": [
      "10-Stream"
    ]
  },
  {
    "Type": "Incus",
    "Os": "Centos",
    "Distribution": "Centos",
    "Name": "centos",
    "Username": "root",
    "Uid": 0,
    "Release": "9-Stream",
    "Url": "https://images.linuxcontainers.org/images/centos/9-Stream/amd64/default/20260125_07%3A08/rootfs.tar.xz",
    "Configured": false,
    "LocalFileName": "3BE1804992BA99CF13A8C4DA4A3BDA49D80FC005B0C6F7AC0794D8FA0A84F169.rootfs.tar.gz",
    "Hash": {
      "Url": "https://images.linuxcontainers.org/images/centos/9-Stream/amd64/default/20260125_07%3A08/SHA256SUMS",
      "Type": "sums",
      "Algorithm": "SHA256"
    },
    "Digest": "3BE1804992BA99CF13A8C4DA4A3BDA49D80FC005B0C6F7AC0794D8FA0A84F169",
    "Size": 108603292,
    "Tags": [
      "9-Stream"
    ]
  },
  {
    "Type": "Incus",
    "Os": "Debian",
    "Distribution": "Debian",
    "Name": "debian",
    "Username": "root",
    "Uid": 0,
    "Release": "bookworm",
    "Url": "https://images.linuxcontainers.org/images/debian/bookworm/amd64/default/20260125_05%3A24/rootfs.tar.xz",
    "Configured": false,
    "LocalFileName": "91220024FF8DCF759F7AC708B25EC1888590D84FDD6BA541E10E1A02719E2F7E.rootfs.tar.gz",
    "Hash": {
      "Url": "https://images.linuxcontainers.org/images/debian/bookworm/amd64/default/20260125_05%3A24/SHA256SUMS",
      "Type": "sums",
      "Algorithm": "SHA256"
    },
    "Digest": "91220024FF8DCF759F7AC708B25EC1888590D84FDD6BA541E10E1A02719E2F7E",
    "Size": 95724272,
    "Tags": [
      "bookworm"
    ]
  },
  {
    "Type": "Incus",
    "Os": "Debian",
    "Distribution": "Debian",
    "Name": "debian",
    "Username": "root",
    "Uid": 0,
    "Release": "bullseye",
    "Url": "https://images.linuxcontainers.org/images/debian/bullseye/amd64/default/20260125_05%3A24/rootfs.tar.xz",
    "Configured": false,
    "LocalFileName": "7D9E40A9E1923A6A5D4CB9A6B2DD8ADC1380AD2520203FCB3F2C42326A5435D1.rootfs.tar.gz",
    "Hash": {
      "Url": "https://images.linuxcontainers.org/images/debian/bullseye/amd64/default/20260125_05%3A24/SHA256SUMS",
      "Type": "sums",
      "Algorithm": "SHA256"
    },
    "Digest": "7D9E40A9E1923A6A5D4CB9A6B2DD8ADC1380AD2520203FCB3F2C42326A5435D1",
    "Size": 91474916,
    "Tags": [
      "bullseye"
    ]
  },
  {
    "Type": "Incus",
    "Os": "Debian",
    "Distribution": "Debian",
    "Name": "debian",
    "Username": "root",
    "Uid": 0,
    "Release": "forky",
    "Url": "https://images.linuxcontainers.org/images/debian/forky/amd64/default/20260125_05%3A24/rootfs.tar.xz",
    "Configured": false,
    "LocalFileName": "511FCC0A8457273EC6960303F36DDCFC8E2CA6184AC74AA509E40568C9EB2B15.rootfs.tar.gz",
    "Hash": {
      "Url": "https://images.linuxcontainers.org/images/debian/forky/amd64/default/20260125_05%3A24/SHA256SUMS",
      "Type": "sums",
      "Algorithm": "SHA256"
    },
    "Digest": "511FCC0A8457273EC6960303F36DDCFC8E2CA6184AC74AA509E40568C9EB2B15",
    "Size": 86631792,
    "Tags": [
      "forky"
    ]
  },
  {
    "Type": "Incus",
    "Os": "Debian",
    "Distribution": "Debian",
    "Name": "debian",
    "Username": "root",
    "Uid": 0,
    "Release": "trixie",
    "Url": "https://images.linuxcontainers.org/images/debian/trixie/amd64/default/20260125_05%3A24/rootfs.tar.xz",
    "Configured": false,
    "LocalFileName": "6194BC290F0B174C6D94211AC49F2FDEC1ACE56B786567A262981729D91D4075.rootfs.tar.gz",
    "Hash": {
      "Url": "https://images.linuxcontainers.org/images/debian/trixie/amd64/default/20260125_05%3A24/SHA256SUMS",
      "Type": "sums",
      "Algorithm": "SHA256"
    },
    "Digest": "6194BC290F0B174C6D94211AC49F2FDEC1ACE56B786567A262981729D91D4075",
    "Size": 87071548,
    "Tags": [
      "trixie"
    ]
  },
  {
    "Type": "Incus",
    "Os": "Devuan",
    "Distribution": "Devuan",
    "Name": "devuan",
    "Username": "root",
    "Uid": 0,
    "Release": "chimaera",
    "Url": "https://images.linuxcontainers.org/images/devuan/chimaera/amd64/default/20260125_11%3A50/rootfs.tar.xz",
    "Configured": false,
    "LocalFileName": "5E77F3DAA879F70CCF2C329A4E04DB3C30FB555E40783737D3F50FA51AE2EA47.rootfs.tar.gz",
    "Hash": {
      "Url": "https://images.linuxcontainers.org/images/devuan/chimaera/amd64/default/20260125_11%3A50/SHA256SUMS",
      "Type": "sums",
      "Algorithm": "SHA256"
    },
    "Digest": "5E77F3DAA879F70CCF2C329A4E04DB3C30FB555E40783737D3F50FA51AE2EA47",
    "Size": 85236036,
    "Tags": [
      "chimaera"
    ]
  },
  {
    "Type": "Incus",
    "Os": "Devuan",
    "Distribution": "Devuan",
    "Name": "devuan",
    "Username": "root",
    "Uid": 0,
    "Release": "daedalus",
    "Url": "https://images.linuxcontainers.org/images/devuan/daedalus/amd64/default/20260125_11%3A50/rootfs.tar.xz",
    "Configured": false,
    "LocalFileName": "16CF24929C2F07336FE36BD4A81D7D906E8799C11C3AD8D095E86863B198665D.rootfs.tar.gz",
    "Hash": {
      "Url": "https://images.linuxcontainers.org/images/devuan/daedalus/amd64/default/20260125_11%3A50/SHA256SUMS",
      "Type": "sums",
      "Algorithm": "SHA256"
    },
    "Digest": "16CF24929C2F07336FE36BD4A81D7D906E8799C11C3AD8D095E86863B198665D",
    "Size": 87967760,
    "Tags": [
      "daedalus"
    ]
  },
  {
    "Type": "Incus",
    "Os": "Devuan",
    "Distribution": "Devuan",
    "Name": "devuan",
    "Username": "root",
    "Uid": 0,
    "Release": "excalibur",
    "Url": "https://images.linuxcontainers.org/images/devuan/excalibur/amd64/default/20260125_11%3A50/rootfs.tar.xz",
    "Configured": false,
    "LocalFileName": "8D335D8366E2F8506F839E3D82179AADE955031009F5DCDBFD4FACDD84C0690D.rootfs.tar.gz",
    "Hash": {
      "Url": "https://images.linuxcontainers.org/images/devuan/excalibur/amd64/default/20260125_11%3A50/SHA256SUMS",
      "Type": "sums",
      "Algorithm": "SHA256"
    },
    "Digest": "8D335D8366E2F8506F839E3D82179AADE955031009F5DCDBFD4FACDD84C0690D",
    "Size": 83688100,
    "Tags": [
      "excalibur"
    ]
  },
  {
    "Type": "Incus",
    "Os": "Fedora",
    "Distribution": "Fedora",
    "Name": "fedora",
    "Username": "root",
    "Uid": 0,
    "Release": "41",
    "Url": "https://images.linuxcontainers.org/images/fedora/41/amd64/default/20260125_20%3A33/rootfs.tar.xz",
    "Configured": false,
    "LocalFileName": "444D4D7091DB6F432B971B833071CE31CCF4F970C592984273E818F505ABA9D9.rootfs.tar.gz",
    "Hash": {
      "Url": "https://images.linuxcontainers.org/images/fedora/41/amd64/default/20260125_20%3A33/SHA256SUMS",
      "Type": "sums",
      "Algorithm": "SHA256"
    },
    "Digest": "444D4D7091DB6F432B971B833071CE31CCF4F970C592984273E818F505ABA9D9",
    "Size": 90750484,
    "Tags": [
      "41"
    ]
  },
  {
    "Type": "Incus",
    "Os": "Fedora",
    "Distribution": "Fedora",
    "Name": "fedora",
    "Username": "root",
    "Uid": 0,
    "Release": "42",
    "Url": "https://images.linuxcontainers.org/images/fedora/42/amd64/default/20260125_20%3A33/rootfs.tar.xz",
    "Configured": false,
    "LocalFileName": "0CBD4AA049EA95B686D8F9261F531780C16B039AB40A4B890BAED5B81932E6F6.rootfs.tar.gz",
    "Hash": {
      "Url": "https://images.linuxcontainers.org/images/fedora/42/amd64/default/20260125_20%3A33/SHA256SUMS",
      "Type": "sums",
      "Algorithm": "SHA256"
    },
    "Digest": "0CBD4AA049EA95B686D8F9261F531780C16B039AB40A4B890BAED5B81932E6F6",
    "Size": 92243640,
    "Tags": [
      "42"
    ]
  },
  {
    "Type": "Incus",
    "Os": "Fedora",
    "Distribution": "Fedora",
    "Name": "fedora",
    "Username": "root",
    "Uid": 0,
    "Release": "43",
    "Url": "https://images.linuxcontainers.org/images/fedora/43/amd64/default/20260125_20%3A33/rootfs.tar.xz",
    "Configured": false,
    "LocalFileName": "31B7B47B010D0A9A55FFE085D1AF1F647525F51405E59DEA8354122EE600EBD1.rootfs.tar.gz",
    "Hash": {
      "Url": "https://images.linuxcontainers.org/images/fedora/43/amd64/default/20260125_20%3A33/SHA256SUMS",
      "Type": "sums",
      "Algorithm": "SHA256"
    },
    "Digest": "31B7B47B010D0A9A55FFE085D1AF1F647525F51405E59DEA8354122EE600EBD1",
    "Size": 96680156,
    "Tags": [
      "43"
    ]
  },
  {
    "Type": "Incus",
    "Os": "Kali",
    "Distribution": "Kali",
    "Name": "kali",
    "Username": "root",
    "Uid": 0,
    "Release": "current",
    "Url": "https://images.linuxcontainers.org/images/kali/current/amd64/default/20260125_17%3A14/rootfs.tar.xz",
    "Configured": false,
    "LocalFileName": "0F0C95CBAA926A411F8A397B680D25939750B1649366561F218994F69A10185D.rootfs.tar.gz",
    "Hash": {
      "Url": "https://images.linuxcontainers.org/images/kali/current/amd64/default/20260125_17%3A14/SHA256SUMS",
      "Type": "sums",
      "Algorithm": "SHA256"
    },
    "Digest": "0F0C95CBAA926A411F8A397B680D25939750B1649366561F218994F69A10185D",
    "Size": 78472076,
    "Tags": [
      "current"
    ]
  },
  {
    "Type": "Incus",
    "Os": "Mint",
    "Distribution": "Mint",
    "Name": "mint",
    "Username": "root",
    "Uid": 0,
    "Release": "ulyana",
    "Url": "https://images.linuxcontainers.org/images/mint/ulyana/amd64/default/20260125_08%3A51/rootfs.tar.xz",
    "Configured": false,
    "LocalFileName": "CD362ED308E463B5F351C68AFEC11BBAFE713E5A11C9EBA26C7E228C860C5174.rootfs.tar.gz",
    "Hash": {
      "Url": "https://images.linuxcontainers.org/images/mint/ulyana/amd64/default/20260125_08%3A51/SHA256SUMS",
      "Type": "sums",
      "Algorithm": "SHA256"
    },
    "Digest": "CD362ED308E463B5F351C68AFEC11BBAFE713E5A11C9EBA26C7E228C860C5174",
    "Size": 205334084,
    "Tags": [
      "ulyana"
    ]
  },
  {
    "Type": "Incus",
    "Os": "Mint",
    "Distribution": "Mint",
    "Name": "mint",
    "Username": "root",
    "Uid": 0,
    "Release": "ulyssa",
    "Url": "https://images.linuxcontainers.org/images/mint/ulyssa/amd64/default/20260125_08%3A51/rootfs.tar.xz",
    "Configured": false,
    "LocalFileName": "A460FA0CE5344A4083B0FE0A95030FAEE9756B09D90C5C8A8BA41EF8E5A382DF.rootfs.tar.gz",
    "Hash": {
      "Url": "https://images.linuxcontainers.org/images/mint/ulyssa/amd64/default/20260125_08%3A51/SHA256SUMS",
      "Type": "sums",
      "Algorithm": "SHA256"
    },
    "Digest": "A460FA0CE5344A4083B0FE0A95030FAEE9756B09D90C5C8A8BA41EF8E5A382DF",
    "Size": 205433900,
    "Tags": [
      "ulyssa"
    ]
  },
  {
    "Type": "Incus",
    "Os": "Mint",
    "Distribution": "Mint",
    "Name": "mint",
    "Username": "root",
    "Uid": 0,
    "Release": "uma",
    "Url": "https://images.linuxcontainers.org/images/mint/uma/amd64/default/20260125_08%3A51/rootfs.tar.xz",
    "Configured": false,
    "LocalFileName": "F2A10C2FA47C9567E2820E42606C6EB182989CC391C5C7552632B8478AC6568F.rootfs.tar.gz",
    "Hash": {
      "Url": "https://images.linuxcontainers.org/images/mint/uma/amd64/default/20260125_08%3A51/SHA256SUMS",
      "Type": "sums",
      "Algorithm": "SHA256"
    },
    "Digest": "F2A10C2FA47C9567E2820E42606C6EB182989CC391C5C7552632B8478AC6568F",
    "Size": 205447268,
    "Tags": [
      "uma"
    ]
  },
  {
    "Type": "Incus",
    "Os": "Mint",
    "Distribution": "Mint",
    "Name": "mint",
    "Username": "root",
    "Uid": 0,
    "Release": "una",
    "Url": "https://images.linuxcontainers.org/images/mint/una/amd64/default/20260125_08%3A51/rootfs.tar.xz",
    "Configured": false,
    "LocalFileName": "9B70260583180D8CE9CB143B0841C64BEE963B46FA92AA9B64DFDEC2D68460DC.rootfs.tar.gz",
    "Hash": {
      "Url": "https://images.linuxcontainers.org/images/mint/una/amd64/default/20260125_08%3A51/SHA256SUMS",
      "Type": "sums",
      "Algorithm": "SHA256"
    },
    "Digest": "9B70260583180D8CE9CB143B0841C64BEE963B46FA92AA9B64DFDEC2D68460DC",
    "Size": 205463988,
    "Tags": [
      "una"
    ]
  },
  {
    "Type": "Incus",
    "Os": "Mint",
    "Distribution": "Mint",
    "Name": "mint",
    "Username": "root",
    "Uid": 0,
    "Release": "vanessa",
    "Url": "https://images.linuxcontainers.org/images/mint/vanessa/amd64/default/20260125_08%3A51/rootfs.tar.xz",
    "Configured": false,
    "LocalFileName": "05293FD09A2649BBC937AEEA8D68B0FC411D500537CDBAD5CE094D3BFC2F5CEE.rootfs.tar.gz",
    "Hash": {
      "Url": "https://images.linuxcontainers.org/images/mint/vanessa/amd64/default/20260125_08%3A51/SHA256SUMS",
      "Type": "sums",
      "Algorithm": "SHA256"
    },
    "Digest": "05293FD09A2649BBC937AEEA8D68B0FC411D500537CDBAD5CE094D3BFC2F5CEE",
    "Size": 242757136,
    "Tags": [
      "vanessa"
    ]
  },
  {
    "Type": "Incus",
    "Os": "Mint",
    "Distribution": "Mint",
    "Name": "mint",
    "Username": "root",
    "Uid": 0,
    "Release": "vera",
    "Url": "https://images.linuxcontainers.org/images/mint/vera/amd64/default/20260125_08%3A51/rootfs.tar.xz",
    "Configured": false,
    "LocalFileName": "886C654729FB3C21DC6ECD28035E369B341BD30BAC1CF071F527DD0ECF90EBC1.rootfs.tar.gz",
    "Hash": {
      "Url": "https://images.linuxcontainers.org/images/mint/vera/amd64/default/20260125_08%3A51/SHA256SUMS",
      "Type": "sums",
      "Algorithm": "SHA256"
    },
    "Digest": "886C654729FB3C21DC6ECD28035E369B341BD30BAC1CF071F527DD0ECF90EBC1",
    "Size": 243116040,
    "Tags": [
      "vera"
    ]
  },
  {
    "Type": "Incus",
    "Os": "Mint",
    "Distribution": "Mint",
    "Name": "mint",
    "Username": "root",
    "Uid": 0,
    "Release": "victoria",
    "Url": "https://images.linuxcontainers.org/images/mint/victoria/amd64/default/20260125_08%3A51/rootfs.tar.xz",
    "Configured": false,
    "LocalFileName": "44072F4AB1326051330EB694AE89C028BF26A6FF47C15C437C690E40BF1F174C.rootfs.tar.gz",
    "Hash": {
      "Url": "https://images.linuxcontainers.org/images/mint/victoria/amd64/default/20260125_08%3A51/SHA256SUMS",
      "Type": "sums",
      "Algorithm": "SHA256"
    },
    "Digest": "44072F4AB1326051330EB694AE89C028BF26A6FF47C15C437C690E40BF1F174C",
    "Size": 243085920,
    "Tags": [
      "victoria"
    ]
  },
  {
    "Type": "Incus",
    "Os": "Mint",
    "Distribution": "Mint",
    "Name": "mint",
    "Username": "root",
    "Uid": 0,
    "Release": "virginia",
    "Url": "https://images.linuxcontainers.org/images/mint/virginia/amd64/default/20260125_08%3A51/rootfs.tar.xz",
    "Configured": false,
    "LocalFileName": "934692889824BA58B8E6651E2313881E3AFC12964113C0C474FCBE4CADB492CF.rootfs.tar.gz",
    "Hash": {
      "Url": "https://images.linuxcontainers.org/images/mint/virginia/amd64/default/20260125_08%3A51/SHA256SUMS",
      "Type": "sums",
      "Algorithm": "SHA256"
    },
    "Digest": "934692889824BA58B8E6651E2313881E3AFC12964113C0C474FCBE4CADB492CF",
    "Size": 243534052,
    "Tags": [
      "virginia"
    ]
  },
  {
    "Type": "Incus",
    "Os": "Mint",
    "Distribution": "Mint",
    "Name": "mint",
    "Username": "root",
    "Uid": 0,
    "Release": "wilma",
    "Url": "https://images.linuxcontainers.org/images/mint/wilma/amd64/default/20260125_08%3A51/rootfs.tar.xz",
    "Configured": false,
    "LocalFileName": "B8BE85A0B0FF239EDB4C6A972E81808C3A177630ED7A8A2F0AED29E6CB0A011F.rootfs.tar.gz",
    "Hash": {
      "Url": "https://images.linuxcontainers.org/images/mint/wilma/amd64/default/20260125_08%3A51/SHA256SUMS",
      "Type": "sums",
      "Algorithm": "SHA256"
    },
    "Digest": "B8BE85A0B0FF239EDB4C6A972E81808C3A177630ED7A8A2F0AED29E6CB0A011F",
    "Size": 130631564,
    "Tags": [
      "wilma"
    ]
  },
  {
    "Type": "Incus",
    "Os": "Nixos",
    "Distribution": "Nixos",
    "Name": "nixos",
    "Username": "root",
    "Uid": 0,
    "Release": "25.11",
    "Url": "https://images.linuxcontainers.org/images/nixos/25.11/amd64/default/20260125_01%3A01/rootfs.tar.xz",
    "Configured": false,
    "LocalFileName": "E823BD59BF68ABFD375F0FC5449D48340AD0A2E6AA5B6260AF17159C6A8B0904.rootfs.tar.gz",
    "Hash": {
      "Url": "https://images.linuxcontainers.org/images/nixos/25.11/amd64/default/20260125_01%3A01/SHA256SUMS",
      "Type": "sums",
      "Algorithm": "SHA256"
    },
    "Digest": "E823BD59BF68ABFD375F0FC5449D48340AD0A2E6AA5B6260AF17159C6A8B0904",
    "Size": 198154792,
    "Tags": [
      "25.11"
    ]
  },
  {
    "Type": "Incus",
    "Os": "Openeuler",
    "Distribution": "Openeuler",
    "Name": "openeuler",
    "Username": "root",
    "Uid": 0,
    "Release": "20.03",
    "Url": "https://images.linuxcontainers.org/images/openeuler/20.03/amd64/default/20260120_15%3A48/rootfs.tar.xz",
    "Configured": false,
    "LocalFileName": "FCDACBF0AA07B5121090F0254D27F7234D8145C3C7E4A2FA1BDCA67B4829592E.rootfs.tar.gz",
    "Hash": {
      "Url": "https://images.linuxcontainers.org/images/openeuler/20.03/amd64/default/20260120_15%3A48/SHA256SUMS",
      "Type": "sums",
      "Algorithm": "SHA256"
    },
    "Digest": "FCDACBF0AA07B5121090F0254D27F7234D8145C3C7E4A2FA1BDCA67B4829592E",
    "Size": 161124832,
    "Tags": [
      "20.03"
    ]
  },
  {
    "Type": "Incus",
    "Os": "Openeuler",
    "Distribution": "Openeuler",
    "Name": "openeuler",
    "Username": "root",
    "Uid": 0,
    "Release": "22.03",
    "Url": "https://images.linuxcontainers.org/images/openeuler/22.03/amd64/default/20260120_15%3A48/rootfs.tar.xz",
    "Configured": false,
    "LocalFileName": "C9818F0FB8C7004F892A87ACCA50EDE1373C100A10AC1319F2C33C0CB6574670.rootfs.tar.gz",
    "Hash": {
      "Url": "https://images.linuxcontainers.org/images/openeuler/22.03/amd64/default/20260120_15%3A48/SHA256SUMS",
      "Type": "sums",
      "Algorithm": "SHA256"
    },
    "Digest": "C9818F0FB8C7004F892A87ACCA50EDE1373C100A10AC1319F2C33C0CB6574670",
    "Size": 129569152,
    "Tags": [
      "22.03"
    ]
  },
  {
    "Type": "Incus",
    "Os": "Openeuler",
    "Distribution": "Openeuler",
    "Name": "openeuler",
    "Username": "root",
    "Uid": 0,
    "Release": "24.03",
    "Url": "https://images.linuxcontainers.org/images/openeuler/24.03/amd64/default/20260120_15%3A48/rootfs.tar.xz",
    "Configured": false,
    "LocalFileName": "7D045602FC98D8EFFB2B28BBC6D45837110BFC88A8F84FB86F44B2DA2A152DF2.rootfs.tar.gz",
    "Hash": {
      "Url": "https://images.linuxcontainers.org/images/openeuler/24.03/amd64/default/20260120_15%3A48/SHA256SUMS",
      "Type": "sums",
      "Algorithm": "SHA256"
    },
    "Digest": "7D045602FC98D8EFFB2B28BBC6D45837110BFC88A8F84FB86F44B2DA2A152DF2",
    "Size": 126648292,
    "Tags": [
      "24.03"
    ]
  },
  {
    "Type": "Incus",
    "Os": "Openeuler",
    "Distribution": "Openeuler",
    "Name": "openeuler",
    "Username": "root",
    "Uid": 0,
    "Release": "25.03",
    "Url": "https://images.linuxcontainers.org/images/openeuler/25.03/amd64/default/20260120_15%3A48/rootfs.tar.xz",
    "Configured": false,
    "LocalFileName": "71A4930F6E7B411DEEBFC900F5274FFE3A4379D64A436387B10C90655F80D0C9.rootfs.tar.gz",
    "Hash": {
      "Url": "https://images.linuxcontainers.org/images/openeuler/25.03/amd64/default/20260120_15%3A48/SHA256SUMS",
      "Type": "sums",
      "Algorithm": "SHA256"
    },
    "Digest": "71A4930F6E7B411DEEBFC900F5274FFE3A4379D64A436387B10C90655F80D0C9",
    "Size": 120295628,
    "Tags": [
      "25.03"
    ]
  },
  {
    "Type": "Incus",
    "Os": "Openeuler",
    "Distribution": "Openeuler",
    "Name": "openeuler",
    "Username": "root",
    "Uid": 0,
    "Release": "25.09",
    "Url": "https://images.linuxcontainers.org/images/openeuler/25.09/amd64/default/20260120_15%3A48/rootfs.tar.xz",
    "Configured": false,
    "LocalFileName": "C81E89F7A5313124C5D16B44F853603FAD9AEB71F9EEC19603E58B7520BA79E2.rootfs.tar.gz",
    "Hash": {
      "Url": "https://images.linuxcontainers.org/images/openeuler/25.09/amd64/default/20260120_15%3A48/SHA256SUMS",
      "Type": "sums",
      "Algorithm": "SHA256"
    },
    "Digest": "C81E89F7A5313124C5D16B44F853603FAD9AEB71F9EEC19603E58B7520BA79E2",
    "Size": 122956788,
    "Tags": [
      "25.09"
    ]
  },
  {
    "Type": "Incus",
    "Os": "Opensuse",
    "Distribution": "Opensuse",
    "Name": "opensuse",
    "Username": "root",
    "Uid": 0,
    "Release": "15.6",
    "Url": "https://images.linuxcontainers.org/images/opensuse/15.6/amd64/default/20260125_04%3A20/rootfs.tar.xz",
    "Configured": false,
    "LocalFileName": "E94AF4BA35237AA49694CBB2F41D0A0103B1F895D7C738318CFD3C7745BB9566.rootfs.tar.gz",
    "Hash": {
      "Url": "https://images.linuxcontainers.org/images/opensuse/15.6/amd64/default/20260125_04%3A20/SHA256SUMS",
      "Type": "sums",
      "Algorithm": "SHA256"
    },
    "Digest": "E94AF4BA35237AA49694CBB2F41D0A0103B1F895D7C738318CFD3C7745BB9566",
    "Size": 42689336,
    "Tags": [
      "15.6"
    ]
  },
  {
    "Type": "Incus",
    "Os": "Opensuse",
    "Distribution": "Opensuse",
    "Name": "opensuse",
    "Username": "root",
    "Uid": 0,
    "Release": "16.0",
    "Url": "https://images.linuxcontainers.org/images/opensuse/16.0/amd64/default/20260125_04%3A20/rootfs.tar.xz",
    "Configured": false,
    "LocalFileName": "1136B27FBB47944956A1CCFD8869E6087AFB668240145CA8C2CC2FC8BCBDA5D6.rootfs.tar.gz",
    "Hash": {
      "Url": "https://images.linuxcontainers.org/images/opensuse/16.0/amd64/default/20260125_04%3A20/SHA256SUMS",
      "Type": "sums",
      "Algorithm": "SHA256"
    },
    "Digest": "1136B27FBB47944956A1CCFD8869E6087AFB668240145CA8C2CC2FC8BCBDA5D6",
    "Size": 41809612,
    "Tags": [
      "16.0"
    ]
  },
  {
    "Type": "Incus",
    "Os": "Opensuse",
    "Distribution": "Opensuse",
    "Name": "opensuse",
    "Username": "root",
    "Uid": 0,
    "Release": "tumbleweed",
    "Url": "https://images.linuxcontainers.org/images/opensuse/tumbleweed/amd64/default/20260125_04%3A20/rootfs.tar.xz",
    "Configured": false,
    "LocalFileName": "E08CD845615CD5761373BBFE8661055B85A6A36499C684C6B8DF5EC570733C46.rootfs.tar.gz",
    "Hash": {
      "Url": "https://images.linuxcontainers.org/images/opensuse/tumbleweed/amd64/default/20260125_04%3A20/SHA256SUMS",
      "Type": "sums",
      "Algorithm": "SHA256"
    },
    "Digest": "E08CD845615CD5761373BBFE8661055B85A6A36499C684C6B8DF5EC570733C46",
    "Size": 41469688,
    "Tags": [
      "tumbleweed"
    ]
  },
  {
    "Type": "Incus",
    "Os": "Openwrt",
    "Distribution": "Openwrt",
    "Name": "openwrt",
    "Username": "root",
    "Uid": 0,
    "Release": "23.05",
    "Url": "https://images.linuxcontainers.org/images/openwrt/23.05/amd64/default/20260125_11%3A57/rootfs.tar.xz",
    "Configured": false,
    "LocalFileName": "3CE02D414CEC0DECEFF170FDD2AE045ECAD74373B14CC45CE5C65F29EBADAB70.rootfs.tar.gz",
    "Hash": {
      "Url": "https://images.linuxcontainers.org/images/openwrt/23.05/amd64/default/20260125_11%3A57/SHA256SUMS",
      "Type": "sums",
      "Algorithm": "SHA256"
    },
    "Digest": "3CE02D414CEC0DECEFF170FDD2AE045ECAD74373B14CC45CE5C65F29EBADAB70",
    "Size": 3810408,
    "Tags": [
      "23.05"
    ]
  },
  {
    "Type": "Incus",
    "Os": "Openwrt",
    "Distribution": "Openwrt",
    "Name": "openwrt",
    "Username": "root",
    "Uid": 0,
    "Release": "24.10",
    "Url": "https://images.linuxcontainers.org/images/openwrt/24.10/amd64/default/20260125_11%3A57/rootfs.tar.xz",
    "Configured": false,
    "LocalFileName": "F8D7298C5B7AD7D4B256763ACC01F6A58A16710111280DD418DB5419B9726045.rootfs.tar.gz",
    "Hash": {
      "Url": "https://images.linuxcontainers.org/images/openwrt/24.10/amd64/default/20260125_11%3A57/SHA256SUMS",
      "Type": "sums",
      "Algorithm": "SHA256"
    },
    "Digest": "F8D7298C5B7AD7D4B256763ACC01F6A58A16710111280DD418DB5419B9726045",
    "Size": 4036372,
    "Tags": [
      "24.10"
    ]
  },
  {
    "Type": "Incus",
    "Os": "Openwrt",
    "Distribution": "Openwrt",
    "Name": "openwrt",
    "Username": "root",
    "Uid": 0,
    "Release": "25.12",
    "Url": "https://images.linuxcontainers.org/images/openwrt/25.12/amd64/default/20260125_11%3A57/rootfs.tar.xz",
    "Configured": false,
    "LocalFileName": "9963C55903FBB0D99AAC025FA98A1403173B8BECAE95D9B84E2773DD97BCED01.rootfs.tar.gz",
    "Hash": {
      "Url": "https://images.linuxcontainers.org/images/openwrt/25.12/amd64/default/20260125_11%3A57/SHA256SUMS",
      "Type": "sums",
      "Algorithm": "SHA256"
    },
    "Digest": "9963C55903FBB0D99AAC025FA98A1403173B8BECAE95D9B84E2773DD97BCED01",
    "Size": 4169948,
    "Tags": [
      "25.12"
    ]
  },
  {
    "Type": "Incus",
    "Os": "Openwrt",
    "Distribution": "Openwrt",
    "Name": "openwrt",
    "Username": "root",
    "Uid": 0,
    "Release": "snapshot",
    "Url": "https://images.linuxcontainers.org/images/openwrt/snapshot/amd64/default/20260125_11%3A57/rootfs.tar.xz",
    "Configured": false,
    "LocalFileName": "88DFEACD9AB652CF5E4012DC7DCC8E84A9C7A6EEB81EC1D9EFB736AFB9C5165B.rootfs.tar.gz",
    "Hash": {
      "Url": "https://images.linuxcontainers.org/images/openwrt/snapshot/amd64/default/20260125_11%3A57/SHA256SUMS",
      "Type": "sums",
      "Algorithm": "SHA256"
    },
    "Digest": "88DFEACD9AB652CF5E4012DC7DCC8E84A9C7A6EEB81EC1D9EFB736AFB9C5165B",
    "Size": 3760332,
    "Tags": [
      "snapshot"
    ]
  },
  {
    "Type": "Incus",
    "Os": "Oracle",
    "Distribution": "Oracle",
    "Name": "oracle",
    "Username": "root",
    "Uid": 0,
    "Release": "7",
    "Url": "https://images.linuxcontainers.org/images/oracle/7/amd64/default/20260125_07%3A46/rootfs.tar.xz",
    "Configured": false,
    "LocalFileName": "9F374AFAF64BC7E86A2776DF7595063788AB22038F1BCD076D10EEE0D3563FF1.rootfs.tar.gz",
    "Hash": {
      "Url": "https://images.linuxcontainers.org/images/oracle/7/amd64/default/20260125_07%3A46/SHA256SUMS",
      "Type": "sums",
      "Algorithm": "SHA256"
    },
    "Digest": "9F374AFAF64BC7E86A2776DF7595063788AB22038F1BCD076D10EEE0D3563FF1",
    "Size": 73186876,
    "Tags": [
      "7"
    ]
  },
  {
    "Type": "Incus",
    "Os": "Oracle",
    "Distribution": "Oracle",
    "Name": "oracle",
    "Username": "root",
    "Uid": 0,
    "Release": "8",
    "Url": "https://images.linuxcontainers.org/images/oracle/8/amd64/default/20260125_07%3A46/rootfs.tar.xz",
    "Configured": false,
    "LocalFileName": "5093610816A62D0EE9A1F753C4F188185741C855B805EC640405C3EFBFFEFB17.rootfs.tar.gz",
    "Hash": {
      "Url": "https://images.linuxcontainers.org/images/oracle/8/amd64/default/20260125_07%3A46/SHA256SUMS",
      "Type": "sums",
      "Algorithm": "SHA256"
    },
    "Digest": "5093610816A62D0EE9A1F753C4F188185741C855B805EC640405C3EFBFFEFB17",
    "Size": 111850224,
    "Tags": [
      "8"
    ]
  },
  {
    "Type": "Incus",
    "Os": "Oracle",
    "Distribution": "Oracle",
    "Name": "oracle",
    "Username": "root",
    "Uid": 0,
    "Release": "9",
    "Url": "https://images.linuxcontainers.org/images/oracle/9/amd64/default/20260125_07%3A46/rootfs.tar.xz",
    "Configured": false,
    "LocalFileName": "BD19F261FD02E23F47AFE7B55056C5C4F6352200A7FC8ADB1EB9B97C3E0D1E7E.rootfs.tar.gz",
    "Hash": {
      "Url": "https://images.linuxcontainers.org/images/oracle/9/amd64/default/20260125_07%3A46/SHA256SUMS",
      "Type": "sums",
      "Algorithm": "SHA256"
    },
    "Digest": "BD19F261FD02E23F47AFE7B55056C5C4F6352200A7FC8ADB1EB9B97C3E0D1E7E",
    "Size": 93300040,
    "Tags": [
      "9"
    ]
  },
  {
    "Type": "Incus",
    "Os": "Plamo",
    "Distribution": "Plamo",
    "Name": "plamo",
    "Username": "root",
    "Uid": 0,
    "Release": "8.x",
    "Url": "https://images.linuxcontainers.org/images/plamo/8.x/amd64/default/20260125_01%3A33/rootfs.tar.xz",
    "Configured": false,
    "LocalFileName": "AA4B752C25CD75449FD497E7865BE90856239729674AA02284B2B893CAAB62BE.rootfs.tar.gz",
    "Hash": {
      "Url": "https://images.linuxcontainers.org/images/plamo/8.x/amd64/default/20260125_01%3A33/SHA256SUMS",
      "Type": "sums",
      "Algorithm": "SHA256"
    },
    "Digest": "AA4B752C25CD75449FD497E7865BE90856239729674AA02284B2B893CAAB62BE",
    "Size": 292112684,
    "Tags": [
      "8.x"
    ]
  },
  {
    "Type": "Incus",
    "Os": "Rockylinux",
    "Distribution": "Rockylinux",
    "Name": "rockylinux",
    "Username": "root",
    "Uid": 0,
    "Release": "10",
    "Url": "https://images.linuxcontainers.org/images/rockylinux/10/amd64/default/20260125_02%3A06/rootfs.tar.xz",
    "Configured": false,
    "LocalFileName": "5648248AEE12AA75581E547DC0AC5C163CC8A5ACDB2EA81AB7CDAD4A44A91B95.rootfs.tar.gz",
    "Hash": {
      "Url": "https://images.linuxcontainers.org/images/rockylinux/10/amd64/default/20260125_02%3A06/SHA256SUMS",
      "Type": "sums",
      "Algorithm": "SHA256"
    },
    "Digest": "5648248AEE12AA75581E547DC0AC5C163CC8A5ACDB2EA81AB7CDAD4A44A91B95",
    "Size": 84900476,
    "Tags": [
      "10"
    ]
  },
  {
    "Type": "Incus",
    "Os": "Rockylinux",
    "Distribution": "Rockylinux",
    "Name": "rockylinux",
    "Username": "root",
    "Uid": 0,
    "Release": "8",
    "Url": "https://images.linuxcontainers.org/images/rockylinux/8/amd64/default/20260125_02%3A06/rootfs.tar.xz",
    "Configured": false,
    "LocalFileName": "BA98DADE4179FDF939AF5D0AA4D6F30AD9D8E81E205E15CE7BDC64FF74FA857D.rootfs.tar.gz",
    "Hash": {
      "Url": "https://images.linuxcontainers.org/images/rockylinux/8/amd64/default/20260125_02%3A06/SHA256SUMS",
      "Type": "sums",
      "Algorithm": "SHA256"
    },
    "Digest": "BA98DADE4179FDF939AF5D0AA4D6F30AD9D8E81E205E15CE7BDC64FF74FA857D",
    "Size": 115234132,
    "Tags": [
      "8"
    ]
  },
  {
    "Type": "Incus",
    "Os": "Rockylinux",
    "Distribution": "Rockylinux",
    "Name": "rockylinux",
    "Username": "root",
    "Uid": 0,
    "Release": "9",
    "Url": "https://images.linuxcontainers.org/images/rockylinux/9/amd64/default/20260125_02%3A06/rootfs.tar.xz",
    "Configured": false,
    "LocalFileName": "00D37B87C973C494DA6483A5B7CE1D15887FF6D7E7D1A85F866047FA623B691F.rootfs.tar.gz",
    "Hash": {
      "Url": "https://images.linuxcontainers.org/images/rockylinux/9/amd64/default/20260125_02%3A06/SHA256SUMS",
      "Type": "sums",
      "Algorithm": "SHA256"
    },
    "Digest": "00D37B87C973C494DA6483A5B7CE1D15887FF6D7E7D1A85F866047FA623B691F",
    "Size": 106611496,
    "Tags": [
      "9"
    ]
  },
  {
    "Type": "Incus",
    "Os": "Slackware",
    "Distribution": "Slackware",
    "Name": "slackware",
    "Username": "root",
    "Uid": 0,
    "Release": "15.0",
    "Url": "https://images.linuxcontainers.org/images/slackware/15.0/amd64/default/20260125_23%3A08/rootfs.tar.xz",
    "Configured": false,
    "LocalFileName": "4098E7CCD909165B82032C17BF9518C7024BDC0B01694F79527C5AD259BBE115.rootfs.tar.gz",
    "Hash": {
      "Url": "https://images.linuxcontainers.org/images/slackware/15.0/amd64/default/20260125_23%3A08/SHA256SUMS",
      "Type": "sums",
      "Algorithm": "SHA256"
    },
    "Digest": "4098E7CCD909165B82032C17BF9518C7024BDC0B01694F79527C5AD259BBE115",
    "Size": 97014272,
    "Tags": [
      "15.0"
    ]
  },
  {
    "Type": "Incus",
    "Os": "Slackware",
    "Distribution": "Slackware",
    "Name": "slackware",
    "Username": "root",
    "Uid": 0,
    "Release": "current",
    "Url": "https://images.linuxcontainers.org/images/slackware/current/amd64/default/20260125_23%3A08/rootfs.tar.xz",
    "Configured": false,
    "LocalFileName": "8779224903304F3DE28EFD7B4420B97132ECF837B86A2A0C7F106222AA8A5073.rootfs.tar.gz",
    "Hash": {
      "Url": "https://images.linuxcontainers.org/images/slackware/current/amd64/default/20260125_23%3A08/SHA256SUMS",
      "Type": "sums",
      "Algorithm": "SHA256"
    },
    "Digest": "8779224903304F3DE28EFD7B4420B97132ECF837B86A2A0C7F106222AA8A5073",
    "Size": 146759624,
    "Tags": [
      "current"
    ]
  },
  {
    "Type": "Incus",
    "Os": "Springdalelinux",
    "Distribution": "Springdalelinux",
    "Name": "springdalelinux",
    "Username": "root",
    "Uid": 0,
    "Release": "7",
    "Url": "https://images.linuxcontainers.org/images/springdalelinux/7/amd64/default/20260125_06%3A38/rootfs.tar.xz",
    "Configured": false,
    "LocalFileName": "F50476B693349E9FBB8C78A9860F0F4216BE858D23A2CD17583C9800F9B3B4D5.rootfs.tar.gz",
    "Hash": {
      "Url": "https://images.linuxcontainers.org/images/springdalelinux/7/amd64/default/20260125_06%3A38/SHA256SUMS",
      "Type": "sums",
      "Algorithm": "SHA256"
    },
    "Digest": "F50476B693349E9FBB8C78A9860F0F4216BE858D23A2CD17583C9800F9B3B4D5",
    "Size": 73538448,
    "Tags": [
      "7"
    ]
  },
  {
    "Type": "Incus",
    "Os": "Springdalelinux",
    "Distribution": "Springdalelinux",
    "Name": "springdalelinux",
    "Username": "root",
    "Uid": 0,
    "Release": "8",
    "Url": "https://images.linuxcontainers.org/images/springdalelinux/8/amd64/default/20260125_06%3A38/rootfs.tar.xz",
    "Configured": false,
    "LocalFileName": "D1AFADE69CFEDEA00EEAAAE7C90837D90D65D37AB283D2D0CFF7F3C4FD253A02.rootfs.tar.gz",
    "Hash": {
      "Url": "https://images.linuxcontainers.org/images/springdalelinux/8/amd64/default/20260125_06%3A38/SHA256SUMS",
      "Type": "sums",
      "Algorithm": "SHA256"
    },
    "Digest": "D1AFADE69CFEDEA00EEAAAE7C90837D90D65D37AB283D2D0CFF7F3C4FD253A02",
    "Size": 110681572,
    "Tags": [
      "8"
    ]
  },
  {
    "Type": "Incus",
    "Os": "Springdalelinux",
    "Distribution": "Springdalelinux",
    "Name": "springdalelinux",
    "Username": "root",
    "Uid": 0,
    "Release": "9",
    "Url": "https://images.linuxcontainers.org/images/springdalelinux/9/amd64/default/20260125_06%3A38/rootfs.tar.xz",
    "Configured": false,
    "LocalFileName": "F8C694B139D921793F9CA396D048D4FBEF750A24F34F221A3BC918F17135333C.rootfs.tar.gz",
    "Hash": {
      "Url": "https://images.linuxcontainers.org/images/springdalelinux/9/amd64/default/20260125_06%3A38/SHA256SUMS",
      "Type": "sums",
      "Algorithm": "SHA256"
    },
    "Digest": "F8C694B139D921793F9CA396D048D4FBEF750A24F34F221A3BC918F17135333C",
    "Size": 89549384,
    "Tags": [
      "9"
    ]
  },
  {
    "Type": "Incus",
    "Os": "Ubuntu",
    "Distribution": "Ubuntu",
    "Name": "ubuntu",
    "Username": "root",
    "Uid": 0,
    "Release": "jammy",
    "Url": "https://images.linuxcontainers.org/images/ubuntu/jammy/amd64/default/20260125_07%3A42/rootfs.tar.xz",
    "Configured": false,
    "LocalFileName": "BF98A219BBA9314A36FB7C4675E35FCA40507E69CC57B6517E0D20987CFE65CD.rootfs.tar.gz",
    "Hash": {
      "Url": "https://images.linuxcontainers.org/images/ubuntu/jammy/amd64/default/20260125_07%3A42/SHA256SUMS",
      "Type": "sums",
      "Algorithm": "SHA256"
    },
    "Digest": "BF98A219BBA9314A36FB7C4675E35FCA40507E69CC57B6517E0D20987CFE65CD",
    "Size": 128548100,
    "Tags": [
      "jammy"
    ]
  },
  {
    "Type": "Incus",
    "Os": "Ubuntu",
    "Distribution": "Ubuntu",
    "Name": "ubuntu",
    "Username": "root",
    "Uid": 0,
    "Release": "noble",
    "Url": "https://images.linuxcontainers.org/images/ubuntu/noble/amd64/default/20260125_07%3A42/rootfs.tar.xz",
    "Configured": false,
    "LocalFileName": "4284F36AB65838A724A0C55A87A9ABDA4A44D56E556C155765E7A6FC1FE86E7A.rootfs.tar.gz",
    "Hash": {
      "Url": "https://images.linuxcontainers.org/images/ubuntu/noble/amd64/default/20260125_07%3A42/SHA256SUMS",
      "Type": "sums",
      "Algorithm": "SHA256"
    },
    "Digest": "4284F36AB65838A724A0C55A87A9ABDA4A44D56E556C155765E7A6FC1FE86E7A",
    "Size": 129845944,
    "Tags": [
      "noble"
    ]
  },
  {
    "Type": "Incus",
    "Os": "Ubuntu",
    "Distribution": "Ubuntu",
    "Name": "ubuntu",
    "Username": "root",
    "Uid": 0,
    "Release": "plucky",
    "Url": "https://images.linuxcontainers.org/images/ubuntu/plucky/amd64/default/20260125_07%3A42/rootfs.tar.xz",
    "Configured": false,
    "LocalFileName": "D50B676730BD120B39EA2F4CC21DC5B090B94E481F3B6C73C2707BF7782BED74.rootfs.tar.gz",
    "Hash": {
      "Url": "https://images.linuxcontainers.org/images/ubuntu/plucky/amd64/default/20260125_07%3A42/SHA256SUMS",
      "Type": "sums",
      "Algorithm": "SHA256"
    },
    "Digest": "D50B676730BD120B39EA2F4CC21DC5B090B94E481F3B6C73C2707BF7782BED74",
    "Size": 115211004,
    "Tags": [
      "plucky"
    ]
  },
  {
    "Type": "Incus",
    "Os": "Ubuntu",
    "Distribution": "Ubuntu",
    "Name": "ubuntu",
    "Username": "root",
    "Uid": 0,
    "Release": "questing",
    "Url": "https://images.linuxcontainers.org/images/ubuntu/questing/amd64/default/20260125_07%3A42/rootfs.tar.xz",
    "Configured": false,
    "LocalFileName": "579510A5ECACB267F777B517EB2D8A45939D88B1CBA393FD055E626EE7C4C37E.rootfs.tar.gz",
    "Hash": {
      "Url": "https://images.linuxcontainers.org/images/ubuntu/questing/amd64/default/20260125_07%3A42/SHA256SUMS",
      "Type": "sums",
      "Algorithm": "SHA256"
    },
    "Digest": "579510A5ECACB267F777B517EB2D8A45939D88B1CBA393FD055E626EE7C4C37E",
    "Size": 120768960,
    "Tags": [
      "questing"
    ]
  },
  {
    "Type": "Incus",
    "Os": "Voidlinux",
    "Distribution": "Voidlinux",
    "Name": "voidlinux",
    "Username": "root",
    "Uid": 0,
    "Release": "current",
    "Url": "https://images.linuxcontainers.org/images/voidlinux/current/amd64/default/20260125_17%3A10/rootfs.tar.xz",
    "Configured": false,
    "LocalFileName": "1481682729C687B90B5D945E01F6A1F8E7D37C742596D6A5699B16E73580039E.rootfs.tar.gz",
    "Hash": {
      "Url": "https://images.linuxcontainers.org/images/voidlinux/current/amd64/default/20260125_17%3A10/SHA256SUMS",
      "Type": "sums",
      "Algorithm": "SHA256"
    },
    "Digest": "1481682729C687B90B5D945E01F6A1F8E7D37C742596D6A5699B16E73580039E",
    "Size": 128439060,
    "Tags": [
      "current"
    ]
  }
]
